Metadata-Version: 2.1
Name: kurvy
Version: 1.0.4
Summary: Curve approximation toolkit
Home-page: https://github.com/celerygemini/kurvy
Author: celerygemini
Classifier: Programming Language :: Python :: 3.9
Classifier: License :: OSI Approved :: MIT License
Classifier: Operating System :: OS Independent
Requires-Python: >=3.9
License-File: LICENSE
